libtable/__init__.py
libtable/_baseclass.py
libtable/_basetablecontrol.py
libtable/table.py
libtable/tablecontrol.py
libtable/tabledit.py
libtable/tableeditcontrol.py
libtable/tableprompt.py
libtable/tableselect.py
libtable/tableselectcontrol.py
libtable-0.3.1.dist-info/WHEEL
libtable-0.3.1.dist-info/METADATA
libtable-0.3.1.dist-info/RECORD
