Metadata-Version: 2.1
Name: libtable
Version: 0.3.1
Summary: Python library for cli tables
Home-page: https://github.com/sguerri/libtable
License: GPL-3.0
Author: Sebastien GUERRI
Author-email: nierrgu@bmel.fr
Requires-Python: >=3.6.2,<4.0
Classifier: License :: OSI Approved :: GNU General Public License v3 (GPLv3)
Classifier: Programming Language :: Python :: 3
Classifier: Programming Language :: Python :: 3.10
Classifier: Programming Language :: Python :: 3.7
Classifier: Programming Language :: Python :: 3.8
Classifier: Programming Language :: Python :: 3.9
Requires-Dist: prompt-toolkit (>=3.0.29,<4.0.0)
Project-URL: Repository, https://github.com/sguerri/libtable
